fpdf/__init__.py
fpdf/fonts.py
fpdf/fpdf.py
fpdf/html.py
fpdf/php.py
fpdf/py3k.py
fpdf/template.py
fpdf/ttfonts.py
reportbro_fpdf-1.7.8.dist-info/DESCRIPTION.rst
reportbro_fpdf-1.7.8.dist-info/METADATA
reportbro_fpdf-1.7.8.dist-info/RECORD
reportbro_fpdf-1.7.8.dist-info/WHEEL
reportbro_fpdf-1.7.8.dist-info/metadata.json
reportbro_fpdf-1.7.8.dist-info/top_level.txt
