Metadata-Version: 2.0
Name: reportbro-fpdf
Version: 1.7.8
Summary: Simple PDF generation for Python
Home-page: https://www.reportbro.com
Author: Olivier PLATHEY ported by Max
Author-email: maxpat78@yahoo.it
Maintainer: Alex Hartmann
Maintainer-email: alex@reportbro.com
License: LGPLv3+
Keywords: pdf,unicode,png,jpg,ttf
Platform: UNKNOWN
Classifier: Development Status :: 5 - Production/Stable
Classifier: Intended Audience :: Developers
Classifier: License :: OSI Approved :: GNU Lesser General Public License v3 (LGPLv3)
Classifier: Programming Language :: Python
Classifier: Programming Language :: Python :: 2.7
Classifier: Programming Language :: Python :: 3.5
Classifier: Programming Language :: Python :: 3.6
Classifier: Operating System :: OS Independent
Classifier: Topic :: Software Development :: Libraries :: PHP Classes
Classifier: Topic :: Software Development :: Libraries :: Python Modules
Classifier: Topic :: Multimedia :: Graphics
Requires-Dist: Pillow (>=4)
Requires-Dist: six
